brag/__init__.py
brag/__main__.py
brag/agents.py
brag/batching.py
brag/cli.py
brag/models.py
brag/progress.py
brag/py.typed
brag/repository.py
brag/text_formatters.py
brag/tokens.py
brag/sources/__init__.py
brag/sources/git_commits.py
brag/sources/github_commits.py
brag_ai-0.1.4.dist-info/METADATA
brag_ai-0.1.4.dist-info/WHEEL
brag_ai-0.1.4.dist-info/entry_points.txt
brag_ai-0.1.4.dist-info/licenses/LICENSE
brag_ai-0.1.4.dist-info/RECORD
