Metadata-Version: 2.4
Name: brag-ai
Version: 0.1.4
Summary: Generate and maintain a brag document automatically from your GitHub contributions, powered by AI.
Project-URL: Homepage, https://github.com/ruancomelli/brag-ai
Project-URL: Documentation, https://www.ruancomelli.com/brag-ai/
Project-URL: Repository, https://github.com/ruancomelli/brag-ai.git
Project-URL: Issues, https://github.com/ruancomelli/brag-ai/issues
Project-URL: Changelog, https://github.com/ruancomelli/brag-ai/blob/main/CHANGELOG.md
Author-email: Ruan Comelli <ruancomelli@gmail.com>
License-Expression: MIT
License-File: LICENSE
Classifier: Development Status :: 4 - Beta
Classifier: Environment :: Console
Classifier: Intended Audience :: Developers
Classifier: Intended Audience :: End Users/Desktop
Classifier: License :: OSI Approved :: MIT License
Classifier: Operating System :: OS Independent
Classifier: Programming Language :: Python
Classifier: Programming Language :: Python :: 3
Classifier: Programming Language :: Python :: 3 :: Only
Classifier: Programming Language :: Python :: 3.12
Classifier: Programming Language :: Python :: 3.13
Classifier: Typing :: Typed
Requires-Python: >=3.12
Requires-Dist: cyclopts>=3.9.2
Requires-Dist: gitpython>=3.1.44
Requires-Dist: loguru>=0.7.3
Requires-Dist: pydantic-ai-slim[anthropic,cohere,groq,mistral,openai,vertexai]>=0.0.43
Requires-Dist: pydantic>=2.10.6
Requires-Dist: pygithub>=2.6.0
Requires-Dist: rich>=14.2.0
